rez/__init__.py
rez/console.py
rez/core.py
rez/effects.py
rez/style.py
rez/utils.py
rezlang-4.0.1.dist-info/METADATA
rezlang-4.0.1.dist-info/WHEEL
rezlang-4.0.1.dist-info/top_level.txt
rezlang-4.0.1.dist-info/RECORD
