Metadata-Version: 2.4
Name: rezlang
Version: 4.0.1
Summary: RezLang+ — made by Rez
Home-page: https://github.com/rez/rezlang
Author: Rez
Author-email: justraih@example.com
Keywords: rezlang console effects fun animation
Classifier: Programming Language :: Python :: 3
Classifier: License :: OSI Approved :: MIT License
Classifier: Operating System :: OS Independent
Classifier: Intended Audience :: Developers
Classifier: Topic :: Software Development :: Libraries :: Python Modules
Requires-Python: >=3.8
Dynamic: author
Dynamic: author-email
Dynamic: classifier
Dynamic: description
Dynamic: description-content-type
Dynamic: home-page
Dynamic: keywords
Dynamic: requires-python
Dynamic: summary
